README.rst
setup.cfg
setup.py
fastbill/__init__.py
fastbill/exceptions.py
fastbill/jsonencoder.py
fastbill/response.py
fastbill/wrapper.py
fastbill.egg-info/PKG-INFO
fastbill.egg-info/SOURCES.txt
fastbill.egg-info/dependency_links.txt
fastbill.egg-info/requires.txt
fastbill.egg-info/top_level.txt