Metadata-Version: 1.1
Name: fastbill
Version: 0.7.3
Summary: A thin python wrapper for the fastbill API
Home-page: http://github.com/stylight/python-fastbill
Author: python-fastbill contributors
Author-email: busdev_engineers@stylight.com
License: MIT License
Keywords: fastbill api
Platform: UNKNOWN
Classifier: Intended Audience :: Developers
Classifier: Topic :: Office/Business
Classifier: Topic :: Office/Business :: Financial
Classifier: License :: OSI Approved
Classifier: License :: OSI Approved :: MIT License
Classifier: Programming Language :: Python
Classifier: Programming Language :: Python :: 2.6
Classifier: Programming Language :: Python :: 2.7
Classifier: Programming Language :: Python :: 3.4
Classifier: Programming Language :: Python :: 3.5
Classifier: Topic :: Software Development :: Libraries :: Python Modules
